LICENSE
MANIFEST.in
README.md
setup.py
examples/add_new_modality.py
examples/simple_config.py
examples/simple_obs_nets.py
examples/simple_train_loop.py
examples/train_bc_rnn.py
robomimic/__init__.py
robomimic.egg-info/PKG-INFO
robomimic.egg-info/SOURCES.txt
robomimic.egg-info/dependency_links.txt
robomimic.egg-info/eager_resources.txt
robomimic.egg-info/requires.txt
robomimic.egg-info/top_level.txt
robomimic/algo/__init__.py
robomimic/algo/algo.py
robomimic/algo/bc.py
robomimic/algo/bcq.py
robomimic/algo/cql.py
robomimic/algo/gl.py
robomimic/algo/hbc.py
robomimic/algo/iris.py
robomimic/algo/td3_bc.py
robomimic/config/__init__.py
robomimic/config/base_config.py
robomimic/config/bc_config.py
robomimic/config/bcq_config.py
robomimic/config/config.py
robomimic/config/cql_config.py
robomimic/config/gl_config.py
robomimic/config/hbc_config.py
robomimic/config/iris_config.py
robomimic/config/td3_bc_config.py
robomimic/envs/__init__.py
robomimic/envs/env_base.py
robomimic/envs/env_gym.py
robomimic/envs/env_ig_momart.py
robomimic/envs/env_robosuite.py
robomimic/exps/templates/bc.json
robomimic/exps/templates/bcq.json
robomimic/exps/templates/cql.json
robomimic/exps/templates/gl.json
robomimic/exps/templates/hbc.json
robomimic/exps/templates/iris.json
robomimic/exps/templates/td3_bc.json
robomimic/models/__init__.py
robomimic/models/base_nets.py
robomimic/models/distributions.py
robomimic/models/obs_nets.py
robomimic/models/policy_nets.py
robomimic/models/vae_nets.py
robomimic/models/value_nets.py
robomimic/scripts/dataset_states_to_obs.py
robomimic/scripts/download_datasets.py
robomimic/scripts/download_momart_datasets.py
robomimic/scripts/extract_obs_from_raw_datasets.sh
robomimic/scripts/generate_config_templates.py
robomimic/scripts/generate_paper_configs.py
robomimic/scripts/get_dataset_info.py
robomimic/scripts/hyperparam_helper.py
robomimic/scripts/playback_dataset.py
robomimic/scripts/run_trained_agent.py
robomimic/scripts/split_train_val.py
robomimic/scripts/train.py
robomimic/scripts/conversion/convert_d4rl.py
robomimic/scripts/conversion/convert_robosuite.py
robomimic/scripts/conversion/convert_roboturk_pilot.py
robomimic/utils/__init__.py
