Metadata-Version: 2.1
Name: robomimic
Version: 0.2.0
Summary: robomimic: A Modular Framework for Robot Learning from Demonstration
Home-page: https://github.com/ARISE-Initiative/robomimic
Author: Ajay Mandlekar, Danfei Xu, Josiah Wong, Soroush Nasiriany, Chen Wang
Author-email: amandlek@cs.stanford.edu
License: UNKNOWN
Platform: UNKNOWN
Requires-Python: >=3
License-File: LICENSE
